whitebit_httpx_client/__init__.py
whitebit_httpx_client-0.6.0.dist-info/licenses/LICENSE
whitebit_httpx_client-0.6.0.dist-info/METADATA
whitebit_httpx_client-0.6.0.dist-info/WHEEL
whitebit_httpx_client-0.6.0.dist-info/top_level.txt
whitebit_httpx_client-0.6.0.dist-info/RECORD
