Metadata-Version: 2.4
Name: whitebit_httpx_client
Version: 0.6.0
Summary: An asynchronous library for interacting with whitebit
Home-page: https://github.com/Grommash9/whitebit_httpx_client
Author: Oleksandr Prudnikov
Author-email: prudnikov21@icloud.com
Project-URL: Documentation, https://grommash9.github.io/whitebit_httpx_client/
Project-URL: Source, https://github.com/Grommash9/whitebit_httpx_client
Keywords: whitebit,whitebit api,whitebit client
Classifier: Development Status :: 3 - Alpha
Classifier: Intended Audience :: Developers
Classifier: License :: OSI Approved :: MIT License
Classifier: Programming Language :: Python :: 3.11
Classifier: Programming Language :: Python :: 3.12
License-File: LICENSE
Requires-Dist: httpx
Requires-Dist: setuptools
Provides-Extra: test
Requires-Dist: hypothesis; extra == "test"
Requires-Dist: ruff; extra == "test"
Requires-Dist: pyproj; extra == "test"
Requires-Dist: pytest; extra == "test"
Requires-Dist: pytest-cov; extra == "test"
Requires-Dist: sphinx; extra == "test"
Requires-Dist: pytest-asyncio; extra == "test"
Requires-Dist: tox; extra == "test"
Requires-Dist: build; extra == "test"
Requires-Dist: vcrpy; extra == "test"
Dynamic: author
Dynamic: author-email
Dynamic: classifier
Dynamic: description
Dynamic: description-content-type
Dynamic: home-page
Dynamic: keywords
Dynamic: license-file
Dynamic: project-url
Dynamic: provides-extra
Dynamic: requires-dist
Dynamic: summary
